odoo_venv/__init__.py
odoo_venv/assets/presets.toml
odoo_venv/cli/__init__.py
odoo_venv/cli/main.py
odoo_venv/exceptions.py
odoo_venv/main.py
odoo_venv/migrations/1_0_0.py
odoo_venv/utils.py
odoo_venv-1.0.1.dist-info/licenses/LICENSE
odoo_venv-1.0.1.dist-info/WHEEL
odoo_venv-1.0.1.dist-info/entry_points.txt
odoo_venv-1.0.1.dist-info/METADATA
odoo_venv-1.0.1.dist-info/RECORD
