Metadata-Version: 2.4
Name: odoo-venv
Version: 1.0.1
Summary: A command-line tool to spin up isolated Odoo dev environment in seconds.
Author: trisdoan
Author-email: trisdoan <doanminhtri8183@gmail.com>
License-Expression: AGPL-3.0
License-File: LICENSE
Requires-Dist: typer
Requires-Dist: typing-extensions
Requires-Dist: tomli
Requires-Dist: packaging>=25.0
Requires-Dist: uv~=0.7.12 ; extra == 'build'
Requires-Python: >=3.10
Provides-Extra: build
